COPYING.rst
MANIFEST.in
README.rst
setup.py
src/django_crystal_big/__init__.py
src/django_crystal_big/models.py
src/django_crystal_big/views.py
src/django_crystal_big.egg-info/PKG-INFO
src/django_crystal_big.egg-info/SOURCES.txt
src/django_crystal_big.egg-info/dependency_links.txt
src/django_crystal_big.egg-info/not-zip-safe
src/django_crystal_big.egg-info/requires.txt
src/django_crystal_big.egg-info/top_level.txt
src/django_crystal_big/static/crystal/index.theme
src/django_crystal_big/static/crystal/readme.txt
src/django_crystal_big/static/crystal/128x128/apps/3d.png
src/django_crystal_big/static/crystal/128x128/apps/All software is current.png
src/django_crystal_big/static/crystal/128x128/apps/Community Help.png
src/django_crystal_big/static/crystal/128x128/apps/Internet Connection Tools.png
src/django_crystal_big/static/crystal/128x128/apps/Iskat.png
src/django_crystal_big/static/crystal/128x128/apps/KDE  Resources Configuration.png
src/django_crystal_big/static/crystal/128x128/apps/Linspire Quickstart Guide.png
src/django_crystal_big/static/crystal/128x128/apps/List manager.png
src/django_crystal_big/static/crystal/128x128/apps/Login Manager.png
src/django_crystal_big/static/crystal/128x128/apps/Network Connection Manager.png
src/django_crystal_big/static/crystal/128x128/apps/Service Manager.png
src/django_crystal_big/static/crystal/128x128/apps/Session Manager.png
src/django_crystal_big/static/crystal/128x128/apps/Startup Wizard.png
src/django_crystal_big/static/crystal/128x128/apps/Synaptics touchpad.png
src/django_crystal_big/static/crystal/128x128/apps/Volume Manager.png
src/django_crystal_big/static/crystal/128x128/apps/Ym.png
src/django_crystal_big/static/crystal/128x128/apps/access.png
src/django_crystal_big/static/crystal/128x128/apps/acroread.png
src/django_crystal_big/static/crystal/128x128/apps/advancedsettings.png
src/django_crystal_big/static/crystal/128x128/apps/agent.png
src/django_crystal_big/static/crystal/128x128/apps/agt_aisles.png
src/django_crystal_big/static/crystal/128x128/apps/agt_announcements.png
src/django_crystal_big/static/crystal/128x128/apps/agt_business.png
src/django_crystal_big/static/crystal/128x128/apps/agt_desktop_enhancements.png
